ftdu.py
ftdu-0.0.1.dist-info/LICENSE
ftdu-0.0.1.dist-info/METADATA
ftdu-0.0.1.dist-info/WHEEL
ftdu-0.0.1.dist-info/top_level.txt
ftdu-0.0.1.dist-info/RECORD
