Metadata-Version: 2.1
Name: ftdu
Version: 0.0.1
Summary: Client to talk with ftDuino via USB 
Home-page: https://github.com/heuer/ftdu/
Author: Lars Heuer
Author-email: heuer@semagia.com
License: BSD
Keywords: fischertechnik,ftduino
Platform: any
Classifier: Development Status :: 4 - Beta
Classifier: Intended Audience :: Developers
Classifier: Intended Audience :: Education
Classifier: License :: OSI Approved :: BSD License
Classifier: Operating System :: OS Independent
Classifier: Programming Language :: Python
Classifier: Programming Language :: Python :: 2
Classifier: Programming Language :: Python :: 2.7
Classifier: Programming Language :: Python :: 3
Classifier: Topic :: Software Development :: Libraries :: Python Modules
Classifier: Topic :: Utilities
Requires-Dist: pyserial (>=3.0)
